rossum_agent/__init__.py
rossum_agent/agent_logging.py
rossum_agent/bedrock_client.py
rossum_agent/py.typed
rossum_agent/redis_storage.py
rossum_agent/rossum_mcp_integration.py
rossum_agent/url_context.py
rossum_agent/user_detection.py
rossum_agent/utils.py
rossum_agent/agent/__init__.py
rossum_agent/agent/core.py
rossum_agent/agent/memory.py
rossum_agent/agent/models.py
rossum_agent/agent/request_classifier.py
rossum_agent/agent/skills.py
rossum_agent/agent/types.py
rossum_agent/api/__init__.py
rossum_agent/api/cli.py
rossum_agent/api/dependencies.py
rossum_agent/api/main.py
rossum_agent/api/models/__init__.py
rossum_agent/api/models/schemas.py
rossum_agent/api/routes/__init__.py
rossum_agent/api/routes/chats.py
rossum_agent/api/routes/files.py
rossum_agent/api/routes/health.py
rossum_agent/api/routes/messages.py
rossum_agent/api/services/__init__.py
rossum_agent/api/services/agent_service.py
rossum_agent/api/services/chat_service.py
rossum_agent/api/services/file_service.py
rossum_agent/assets/Primary_light_logo.png
rossum_agent/prompts/__init__.py
rossum_agent/prompts/base_prompt.py
rossum_agent/prompts/system_prompt.py
rossum_agent/skills/hook-debugging.md
rossum_agent/skills/organization-setup.md
rossum_agent/skills/rossum-deployment.md
rossum_agent/skills/schema-patching.md
rossum_agent/skills/schema-pruning.md
rossum_agent/skills/ui-settings.md
rossum_agent/streamlit_app/__init__.py
rossum_agent/streamlit_app/app.py
rossum_agent/streamlit_app/beep_sound.py
rossum_agent/streamlit_app/cli.py
rossum_agent/streamlit_app/render_modules.py
rossum_agent/streamlit_app/response_formatting.py
rossum_agent/tools/__init__.py
rossum_agent/tools/core.py
rossum_agent/tools/deploy.py
rossum_agent/tools/dynamic_tools.py
rossum_agent/tools/file_tools.py
rossum_agent/tools/formula.py
rossum_agent/tools/skills.py
rossum_agent/tools/spawn_mcp.py
rossum_agent/tools/subagents/__init__.py
rossum_agent/tools/subagents/base.py
rossum_agent/tools/subagents/hook_debug.py
rossum_agent-1.0.0rc1.dist-info/licenses/LICENSE
rossum_agent-1.0.0rc1.dist-info/METADATA
rossum_agent-1.0.0rc1.dist-info/WHEEL
rossum_agent-1.0.0rc1.dist-info/entry_points.txt
rossum_agent-1.0.0rc1.dist-info/top_level.txt
rossum_agent-1.0.0rc1.dist-info/RECORD
