Metadata-Version: 2.4
Name: rossum-agent
Version: 1.0.0rc1
Summary: AI agent toolkit for Rossum: document workflows conversationally, debug pipelines automatically, and enable agentic configuration of intelligent document processing.
Author-email: "Dan Stancl (Rossum AI)" <daniel.stancl@gmail.com>
License: MIT
Keywords: agent,rossum,document-processing,ai
Classifier: Development Status :: 4 - Beta
Classifier: License :: OSI Approved :: MIT License
Classifier: Programming Language :: Python :: 3
Classifier: Programming Language :: Python :: 3.12
Classifier: Programming Language :: Python :: 3.13
Classifier: Programming Language :: Python :: 3.14
Classifier: Intended Audience :: Developers
Classifier: Topic :: Scientific/Engineering :: Artificial Intelligence
Classifier: Topic :: Software Development :: Libraries :: Python Modules
Requires-Python: >=3.12
License-File: LICENSE
Requires-Dist: anthropic>=0.75.0
Requires-Dist: boto3>=1.0
Requires-Dist: cryptography>=41.0
Requires-Dist: ddgs>=9.9.0
Requires-Dist: fastmcp>=2.13.0
Requires-Dist: httpx>=0.27.0
Requires-Dist: jinja2>=3.0
Requires-Dist: PyJWT>=2.8
Requires-Dist: pyyaml>=6.0
Requires-Dist: python-dotenv
Requires-Dist: requests>=2.32
Requires-Dist: rossum-api>=3.8.0
Requires-Dist: rossum-deploy>=0.1.0
Requires-Dist: rossum-mcp>=1.0.1
Provides-Extra: api
Requires-Dist: fastapi>=0.115.0; extra == "api"
Requires-Dist: pydantic>2.0.0; extra == "api"
Requires-Dist: python-multipart>=0.0.22; extra == "api"
Requires-Dist: redis>=7.0.0; extra == "api"
Requires-Dist: slowapi>=0.1.9; extra == "api"
Requires-Dist: sse-starlette>=2.0.0; extra == "api"
Requires-Dist: uvicorn[standard]>=0.32.0; extra == "api"
Provides-Extra: docs
Requires-Dist: myst-parser>=2.0.0; extra == "docs"
Requires-Dist: sphinx>=7.0.0; extra == "docs"
Requires-Dist: sphinx-autodoc-typehints>=1.25.0; extra == "docs"
Requires-Dist: sphinx-copybutton>=0.5.2; extra == "docs"
Requires-Dist: sphinx-rtd-theme>=2.0.0; extra == "docs"
Provides-Extra: streamlit
Requires-Dist: pyperclip>=1.0; extra == "streamlit"
Requires-Dist: redis>=7.0.0; extra == "streamlit"
Requires-Dist: streamlit>=1.28.0; extra == "streamlit"
Provides-Extra: tests
Requires-Dist: coverage>=7.0.0; extra == "tests"
Requires-Dist: httpx>=0.27.0; extra == "tests"
Requires-Dist: pytest>=7.0.0; extra == "tests"
Requires-Dist: pytest-asyncio>=0.21.0; extra == "tests"
Requires-Dist: pytest-cov>=4.0.0; extra == "tests"
Requires-Dist: redis>=7.0.0; extra == "tests"
Requires-Dist: streamlit>=1.28.0; extra == "tests"
Provides-Extra: all
Requires-Dist: coverage>=7.0.0; extra == "all"
Requires-Dist: fastapi>=0.115.0; extra == "all"
Requires-Dist: httpx>=0.27.0; extra == "all"
Requires-Dist: myst-parser>=2.0.0; extra == "all"
Requires-Dist: pydantic>2.0.0; extra == "all"
Requires-Dist: pyperclip>=1.0; extra == "all"
Requires-Dist: pytest>=7.0.0; extra == "all"
Requires-Dist: pytest-asyncio>=0.21.0; extra == "all"
Requires-Dist: pytest-cov>=4.0.0; extra == "all"
Requires-Dist: python-multipart>=0.0.22; extra == "all"
Requires-Dist: redis>=7.0.0; extra == "all"
Requires-Dist: slowapi>=0.1.9; extra == "all"
Requires-Dist: sphinx>=7.0.0; extra == "all"
Requires-Dist: sphinx-autodoc-typehints>=1.25.0; extra == "all"
Requires-Dist: sphinx-copybutton>=0.5.2; extra == "all"
Requires-Dist: sphinx-rtd-theme>=2.0.0; extra == "all"
Requires-Dist: sse-starlette>=2.0.0; extra == "all"
Requires-Dist: streamlit>=1.28.0; extra == "all"
Requires-Dist: uvicorn[standard]>=0.32.0; extra == "all"
Dynamic: license-file
